goat_wallets/web3/__init__.py
goat_wallets/web3/wallet.py
goat_sdk_wallet_web3-0.1.5.dist-info/METADATA
goat_sdk_wallet_web3-0.1.5.dist-info/WHEEL
goat_sdk_wallet_web3-0.1.5.dist-info/RECORD
